harman_demo/__init__.py
harman_demo-0.1.0.dist-info/WHEEL
harman_demo-0.1.0.dist-info/METADATA
harman_demo-0.1.0.dist-info/RECORD
