Metadata-Version: 2.1
Name: harman-demo
Version: 0.1.0
Summary: 
Author: Harmandeep Singh Dubb
Author-email: harmand1999@gmail.com
Requires-Python: >=3.7,<4.0
Classifier: Programming Language :: Python :: 3
Classifier: Programming Language :: Python :: 3.7
Classifier: Programming Language :: Python :: 3.8
Requires-Dist: PyGithub (>=1.51,<2.0)
Requires-Dist: pandas (>=1.0.3,<2.0.0)
